{
  "name": "Order",
  "title": "Бездна",
  "description": "Рили фан парт бкс хир ви гоинг ту хенг аут",
  "author": "-",
  "version": "0.01.1",
  "compatibility": {
    "minimum": "11",
    "verified": "11"
  },
  "scripts": [
    "scripts/debuff-script.js",
    "scripts/tabs.js"
  ],
  "esmodules": [
    "Order.js",
    "scripts/tabs.js",
    "scripts/debuff-script.js"
  ],
  "styles": [
    "Order.css",
    "SkillAndSpells.css"
  ],
  "packs": [
    {
      "name": "rasy",
      "label": "Расы",
      "path": "packs/rasy",
      "type": "Item",
      "system": "Order"
    },
    {
      "name": "rasovye-navyki",
      "label": "Расовые навыки",
      "path": "packs/rasovye-navyki",
      "type": "Item",
      "system": "Order"
    }
  ],
  "languages": [
    {
      "lang": "ru",
      "name": "Русский",
      "path": "lang/ru.json"
    },
    {
      "lang": "en",
      "name": "English (placeholder)",
      "path": "lang/en.json"
    }
  ],
  "gridDistance": 5,
  "gridUnits": "m"
}